ewelink/__init__.py
ewelink/ewelink.py
pyewelink-0.2.dist-info/METADATA
pyewelink-0.2.dist-info/WHEEL
pyewelink-0.2.dist-info/entry_points.txt
pyewelink-0.2.dist-info/top_level.txt
pyewelink-0.2.dist-info/RECORD
